setup.py
jim/__init__.py
jim/config.py
jim/utils.py
loggers/__init__.py
loggers/client_log_config.py
message_client_sheludchenkov.egg-info/PKG-INFO
message_client_sheludchenkov.egg-info/SOURCES.txt
message_client_sheludchenkov.egg-info/dependency_links.txt
message_client_sheludchenkov.egg-info/requires.txt
message_client_sheludchenkov.egg-info/top_level.txt
metaclasses/__init__.py
metaclasses/meta.py
storage/__init__.py
storage/client_db.py